[
  {
    "company": null,
    "email3": null,
    "aday": null,
    "ayear": null,
    "telephone": "",
    "middlename": null,
    "all_emails_from_home_page": null,
    "amonth": null,
    "work": null,
    "address": "",
    "mobile": null,
    "id": null,
    "byear": null,
    "email_": "",
    "title": null,
    "all_phones_from_home_page": null,
    "py/object": "model.user.User",
    "fax": null,
    "nickname": null,
    "bday": null,
    "email2": null,
    "secondaryphone": null,
    "bmonth": null,
    "homepage": null,
    "firstname": "",
    "lastname": ""
  },
  {
    "company": null,
    "email3": null,
    "aday": null,
    "ayear": null,
    "telephone": "telephones 7 a",
    "middlename": null,
    "all_emails_from_home_page": null,
    "amonth": null,
    "work": null,
    "address": "addressc / & = _ G",
    "mobile": null,
    "id": null,
    "byear": null,
    "email_": "email_O b \\",
    "title": null,
    "all_phones_from_home_page": null,
    "py/object": "model.user.User",
    "fax": null,
    "nickname": null,
    "bday": null,
    "email2": null,
    "secondaryphone": null,
    "bmonth": null,
    "homepage": null,
    "firstname": "firstname3 9 K g",
    "lastname": "lastname6 7   N f @ @ . 9 ~ ; L , & b"
  },
  {
    "company": null,
    "email3": null,
    "aday": null,
    "ayear": null,
    "telephone": "telephoneN | ) A R j ^ S n R ? z 8 V Q g s 4 $",
    "middlename": null,
    "all_emails_from_home_page": null,
    "amonth": null,
    "work": null,
    "address": "address  ~   6 k",
    "mobile": null,
    "id": null,
    "byear": null,
    "email_": "email_3 a",
    "title": null,
    "all_phones_from_home_page": null,
    "py/object": "model.user.User",
    "fax": null,
    "nickname": null,
    "bday": null,
    "email2": null,
    "secondaryphone": null,
    "bmonth": null,
    "homepage": null,
    "firstname": "firstname2 4",
    "lastname": "lastname  ; } [   o z d [  "
  },
  {
    "company": null,
    "email3": null,
    "aday": null,
    "ayear": null,
    "telephone": "telephone6 *",
    "middlename": null,
    "all_emails_from_home_page": null,
    "amonth": null,
    "work": null,
    "address": "address- # T   k",
    "mobile": null,
    "id": null,
    "byear": null,
    "email_": "email_  b i [ e } t t",
    "title": null,
    "all_phones_from_home_page": null,
    "py/object": "model.user.User",
    "fax": null,
    "nickname": null,
    "bday": null,
    "email2": null,
    "secondaryphone": null,
    "bmonth": null,
    "homepage": null,
    "firstname": "firstname+ o   h h",
    "lastname": "lastname^ K Y P = g * u J %"
  },
  {
    "company": null,
    "email3": null,
    "aday": null,
    "ayear": null,
    "telephone": "telephone/ .   z ; ; ; # - h % ` V W 7 7 O + d",
    "middlename": null,
    "all_emails_from_home_page": null,
    "amonth": null,
    "work": null,
    "address": "address. # T w e 1 W / v '",
    "mobile": null,
    "id": null,
    "byear": null,
    "email_": "email_U ! u d 5 T 0 I { s   ] l T & | T",
    "title": null,
    "all_phones_from_home_page": null,
    "py/object": "model.user.User",
    "fax": null,
    "nickname": null,
    "bday": null,
    "email2": null,
    "secondaryphone": null,
    "bmonth": null,
    "homepage": null,
    "firstname": "firstnameR",
    "lastname": "lastnameZ \\ x r - u V $   ; W > 9   & n"
  },
  {
    "company": null,
    "email3": null,
    "aday": null,
    "ayear": null,
    "telephone": "telephone  <",
    "middlename": null,
    "all_emails_from_home_page": null,
    "amonth": null,
    "work": null,
    "address": "address# m Q C A : c G m   0 + x W G O B",
    "mobile": null,
    "id": null,
    "byear": null,
    "email_": "email_  D",
    "title": null,
    "all_phones_from_home_page": null,
    "py/object": "model.user.User",
    "fax": null,
    "nickname": null,
    "bday": null,
    "email2": null,
    "secondaryphone": null,
    "bmonth": null,
    "homepage": null,
    "firstname": "firstname",
    "lastname": "lastnames m ( # Q $ % h j \" X _ M 1"
  }
]